tidyexc/__init__.py
tidyexc/exc.py
tidyexc/utils.py
tidyexc/views.py
tidyexc-0.9.0.dist-info/LICENSE.txt
tidyexc-0.9.0.dist-info/WHEEL
tidyexc-0.9.0.dist-info/METADATA
tidyexc-0.9.0.dist-info/RECORD
