Metadata-Version: 2.1
Name: tidyexc
Version: 0.9.0
Summary: An exception class inspired by the tidyverse style guide.
Home-page: https://github.com/kalekundert/tidyexc
Author: Kale Kundert
Author-email: kale@thekunderts.net
Requires-Python: ~=3.6
Classifier: Programming Language :: Python :: 3
Classifier: License :: OSI Approved :: MIT License
Requires-Dist: sphinx ; extra == "doc"
Requires-Dist: sphinx_rtd_theme ; extra == "doc"
Requires-Dist: autoclasstoc ; extra == "doc"
Requires-Dist: pytest ; extra == "test"
Requires-Dist: pytest-cov ; extra == "test"
Requires-Dist: coveralls ; extra == "test"
Project-URL: Bug Tracker, https://github.com/kalekundert/tidyexc/issues
Project-URL: Continuous Integration, https://github.com/kalekundert/tidyexc/actions
Project-URL: Documentation, https://tidyexc.readthedocs.io/en/latest/
Project-URL: Test Coverage, https://coveralls.io/github/kalekundert/tidyexc
Project-URL: Version Control, https://github.com/kalekundert/tidyexc
Provides-Extra: doc
Provides-Extra: test
